memory.v
module memory_1bit (
    input d,
    input reset,
    input clock,
    input enable,
    output q, done
);

reg d_reg;

always @(posedge clock or posedge reset) begin
    if (reset) begin
        d_reg <= 1'b0;
    end else begin
        d_reg <= d;
    end
end

assign q = d_reg;

endmodule

module memory_8bit (
    input [7:0] a,
    input [7:0] w,
    input reset, 
    input clock,
    output reg [7:0] q,
    output reg done,
    input enable
);

reg [7:0] d;

always @(posedge clock or posedge reset) begin
    if (reset) begin
        done <= 1'b0;
        d <= 8'b0;
    end else begin
        if (enable) begin
        d <= a;
        done <= 1'b1;
        end
    end

    if (d != 8'h01)begin 
        q <= d;
        done <= 1'b1;
    end else begin 
        q <= w;
        done <= 1'b1;
    end
end

endmodule

module memory_16bit (
    input [15:0] d,         //input masukan
    input reset,
    input clock,
    input enable,
    output [15:0] q,       //output
    output done
);

reg [15:0] q_reg;
reg done_reg;

always @(posedge clock or posedge reset) begin
    if (reset) begin
        q_reg <= 16'b0;
        done_reg <= 1'b0;
    end else begin
        if (enable) begin
            q_reg <= d;
            done_reg <= 1'b1;
        end
    end
end

assign q = q_reg;
assign done = done_reg;

endmodule

sim/memory8_tb.v
module memory_8bit_tb;
reg [7:0] a;
reg [7:0] w;
reg reset;
reg clock;
wire [7:0] q;
wire done;
reg enable;

memory_8bit memory8_uut(
    .a(a),
    .w(w),
    .reset(reset), 
    .clock(clock),
    .q(q),
    .done(done),
    .enable(enable)
);

initial begin
    clock <= 1'b0;
    forever begin
        #1 clock = ~clock;
    end
end

initial begin
    a <= 8'b00000000;
    reset <= 1'b0;
    $dumpfile("memory_test.vcd");
    $dumpvars(0, memory_8bit_tb);
    #50;
    enable <= 1'b1;
    a <= 8'b1010101;
    #50;

    enable <= 1'b1;
    reset <= 1'b1;
    #50;
    a <= 8'b001010;
        #50;
    enable <= 1'b1;
    a <= 8'b1;
    #50;

    enable <= 1'b1;
    reset <= 1'b1;
    #50;
    a <= 8'b011001;
    $finish;
end

endmodule

sim/memory_test.vcd
$date
	Wed Oct 25 16:13:47 2023
$end
$version
	Icarus Verilog
$end
$timescale
	1s
$end
$scope module memory_8bit_tb $end
$var wire 8 ! q [7:0] $end
$var wire 1 " done $end
$var reg 8 # a [7:0] $end
$var reg 1 $ clock $end
$var reg 1 % enable $end
$var reg 1 & reset $end
$var reg 8 ' w [7:0] $end
$scope module memory8_uut $end
$var wire 8 ( a [7:0] $end
$var wire 1 $ clock $end
$var wire 1 % enable $end
$var wire 1 & reset $end
$var wire 8 ) w [7:0] $end
$var reg 8 * d [7:0] $end
$var reg 1 " done $end
$var reg 8 + q [7:0] $end
$upscope $end
$upscope $end
$enddefinitions $end
#0
$dumpvars
bx +
bx *
bx )
b0 (
bx '
0&
x%
0$
b0 #
x"
bx !
$end
#191896070

0$
#3
1$
#4
0$
#5
1$
#6
0$
#7
1$
#8
0$
#9
1$
#10
0$
#11
1$
#12
0$
#13
1$
#14
0$
#15
1$
#16
0$
#17
1$
#18
0$
#19
1$
#20
0$
#21
1$
#22
0$
#23
1$
#24
0$
#25
1$
#26
0$
#27
1$
#28
0$
#29
1$
#30
0$
#31
1$
#32
0$
#33
1$
#34
0$
#35
1$
#36
0$
#37
1$
#38
0$
#39
1$
#40
0$
#41
1$
#42
0$
#43
1$
#44
0$
#45
1$
#46
0$
#47
1$
#48
0$
#49
1$
#50
b1010101 #
b1010101 (
1%
0$
#51
b1010101 *
1$
#52
0$
#53
b1010101 !
b1010101 +
1$
#54
0$
#55
1$
#56
0$
#57
1$
#58
0$
#59
1$
#60
0$
#61
1$
#62
0$
#63
1$
#64
0$
#65
1$
#66
0$
#67
1$
#68
0$
#69
1$
#70
0$
#71
1$
#72
0$
#73
1$
#74
0$
#75
1$
#76
0$
#77
1$
#78
0$
#79
1$
#80
0$
#81
1$
#82
0$
#83
1$
#84
0$
#85
1$
#86
0$
#87
1$
#88
0$
#89
1$
#90
0$
#91
1$
#92
0$
#93
1$
#94
0$
#95
1$
#96
0$
#97
1$
#98
0$
#99
1$
#100
b0 *
1"
1&
0$
#101
b0 !
b0 +
1"
1$
#102
0$
#103
1"
1$
#104
0$
#105
1"
1$
#106
0$
#107
1"
1$
#108
0$
#109
1"
1$
#110
0$
#111
1"
1$
#112
0$
#113
1"
1$
#114
0$
#115
1"
1$
#116
0$
#117
1"
1$
#118
0$
#119
1"
1$
#120
0$
#121
1"
1$
#122
0$
#123
1"
1$
#124
0$
#125
1"
1$
#126
0$
#127
1"
1$
#128
0$
#129
1"
1$
#130
0$
#131
1"
1$
#132
0$
#133
1"
1$
#134
0$
#135
1"
1$
#136
0$
#137
1"
1$
#138
0$
#139
1"
1$
#140
0$
#141
1"
1$
#142
0$
#143
1"
1$
#144
0$
#145
1"
1$
#146
0$
#147
1"
1$
#148
0$
#149
1"
1$
#150
b1010 #
b1010 (
0$
#151
1"
1$
#152
0$
#153
1"
1$
#154
0$
#155
1"
1$
#156
0$
#157
1"
1$
#158
0$
#159
1"
1$
#160
0$
#161
1"
1$
#162
0$
#163
1"
1$
#164
0$
#165
1"
1$
#166
0$
#167
1"
1$
#168
0$
#169
1"
1$
#170
0$
#171
1"
1$
#172
0$
#173
1"
1$
#174
0$
#175
1"
1$
#176
0$
#177
1"
1$
#178
0$
#179
1"
1$
#180
0$
#181
1"
1$
#182
0$
#183
1"
1$
#184
0$
#185
1"
1$
#186
0$
#187
1"
1$
#188
0$
#189
1"
1$
#190
0$
#191
1"
1$
#192
0$
#193
1"
1$
#194
0$
#195
1"
1$
#196
0$
#197
1"
1$
#198
0$
#199
1"
1$
#200
b1 #
b1 (
0$
#201
1"
1$
#202
0$
#203
1"
1$
#204
0$
#205
1"
1$
#206
0$
#207
1"
1$
#208
0$
#209
1"
1$
#210
0$
#211
1"
1$
#212
0$
#213
1"
1$
#214
0$
#215
1"
1$
#216
0$
#217
1"
1$
#218
0$
#219
1"
1$
#220
0$
#221
1"
1$
#222
0$
#223
1"
1$
#224
0$
#225
1"
1$
#226
0$
#227
1"
1$
#228
0$
#229
1"
1$
#230
0$
#231
1"
1$
#232
0$
#233
1"
1$
#234
0$
#235
1"
1$
#236
0$
#237
1"
1$
#238
0$
#239
1"
1$
#240
0$
#241
1"
1$
#242
0$
#243
1"
1$
#244
0$
#245
1"
1$
#246
0$
#247
1"
1$
#248
0$
#249
1"
1$
#250
0$
#251
1"
1$
#252
0$
#253
1"
1$
#254
0$
#255
1"
1$
#256
0$
#257
1"
1$
#258
0$
#259
1"
1$
#260
0$
#261
1"
1$
#262
0$
#263
1"
1$
#264
0$
#265
1"
1$
#266
0$
#267
1"
1$
#268
0$
#269
1"
1$
#270
0$
#271
1"
1$
#272
0$
#273
1"
1$
#274
0$
#275
1"
1$
#276
0$
#277
1"
1$
#278
0$
#279
1"
1$
#280
0$
#281
1"
1$
#282
0$
#283
1"
1$
#284
0$
#285
1"
1$
#286
0$
#287
1"
1$
#288
0$
#289
1"
1$
#290
0$
#291
1"
1$
#292
0$
#293
1"
1$
#294
0$
#295
1"
1$
#296
0$
#297
1"
1$
#298
0$
#299
1"
1$
#300
b11001 #
b11001 (
0$
